sansio_lsp_client/__init__.py
sansio_lsp_client/client.py
sansio_lsp_client/events.py
sansio_lsp_client/io_handler.py
sansio_lsp_client/py.typed
sansio_lsp_client/structs.py
sansio_lsp_client-0.13.0.dist-info/LICENSE
sansio_lsp_client-0.13.0.dist-info/METADATA
sansio_lsp_client-0.13.0.dist-info/WHEEL
sansio_lsp_client-0.13.0.dist-info/RECORD
