Metadata-Version: 2.3
Name: sansio-lsp-client
Version: 0.13.0
Summary: An implementation of the client side of the LSP protocol, useful for embedding easily in your editor.
License: MIT
Keywords: sansio,languageserver
Author: Purple Myst
Author-email: PurpleMyst@users.noreply.github.com
Requires-Python: >=3.10
Classifier: License :: OSI Approved :: MIT License
Classifier: Programming Language :: Python :: 3
Classifier: Programming Language :: Python :: 3.10
Classifier: Programming Language :: Python :: 3.11
Classifier: Programming Language :: Python :: 3.12
Classifier: Programming Language :: Python :: 3.13
Requires-Dist: black (>=24.4.2,<25.0.0)
Requires-Dist: dataclasses (>=0.8,<0.9) ; python_version == "3.6"
Requires-Dist: mypy (>=1.10.0,<2.0.0)
Requires-Dist: pydantic (>=2.0.0,<3.0.0)
Project-URL: Repository, https://github.com/PurpleMyst/sansio-lsp-client
